{
  "resourceType": "http://smart.who.int/pcmt/StructureDefinition/Product",
  "status": "active",
  "name": [
    {
      "nameType": "official",
      "value": "Imvanex® (also approved under the name of JYNNEOS by the USFDA and IMVAMUNE by Health Canada)"
    }
  ],
  "manufacturer": {
    "reference": "Organization/Manufacturer49ba2034b576b9b30559303e880f9bc7"
  },
  "doseQuantity": {
    "value": 1,
    "code": "doses",
    "system": "http://unitsofmeasure.org"
  },
  "classification": [
    {
      "coding": [
        {
          "code": "SmallpoxandMpoxvaccineLi"
        }
      ]
    }
  ],
  "unitOfUse": {
    "coding": [
      {
        "code": "doses"
      }
    ]
  },
  "dosageForm": {
    "coding": [
      {
        "code": "Vial"
      }
    ]
  }
}