{
  "resourceType": "http://smart.who.int/pcmt-vaxprequal/StructureDefinition/PreQualDBwithIds",
  "dateOfPrequal": "2019-12-27",
  "vaccineType": {
    "coding": [
      {
        "code": "InfluenzaseasonalQuadriv",
        "display": "Influenza, seasonal (Quadrivalent)"
      }
    ]
  },
  "commercialName": "SKYCellflu Quadrivalent inj.",
  "presentation": {
    "coding": [
      {
        "system": "https://extranet.who.int/prequal/vaccines/prequalified-vaccines",
        "code": "Vial",
        "display": "Vial"
      }
    ]
  },
  "numDoses": 1,
  "manufacturer": {
    "text": "SK Bioscience Co., Ltd."
  },
  "responsibleNRA": {
    "text": "Ministry of Food and Drug Safety"
  },
  "index": {
    "value": "857b54237833aa49172d24b749788cd8"
  },
  "manufacturerReference": {
    "reference": "Organization/Manufacturer00bfdffd8d8dbe60aabda0191bb814ec"
  },
  "responsibleNRAReference": {
    "reference": "Organization/Holderd4e6bca678dea34fa256538a18200187"
  },
  "productReference": {
    "reference": "http://smart.who.int/pcmt/StructureDefinition/Product/InfluenzaseasonalQuadrivProduct857b54237833aa49172d24b749788cd8"
  }
}