{
  "resourceType": "http://smart.who.int/pcmt-vaxprequal/StructureDefinition/PreQualDBwithIds",
  "dateOfPrequal": "2023-07-06",
  "vaccineType": {
    "coding": [
      {
        "code": "MenigococcalACYWXPolysac",
        "display": "Menigococcal ACYWX (Polysaccharide conjugate)"
      }
    ]
  },
  "commercialName": "MenFive™",
  "presentation": {
    "coding": [
      {
        "system": "https://extranet.who.int/prequal/vaccines/prequalified-vaccines",
        "code": "VialAmpoule",
        "display": "Vial + Ampoule"
      }
    ]
  },
  "numDoses": 1,
  "manufacturer": {
    "text": "Serum Institute of India Pvt. Ltd."
  },
  "responsibleNRA": {
    "text": "Central Drugs Standard Control Organization"
  },
  "index": {
    "value": "62f4ead3da74f2f31a51006339af12fe"
  },
  "manufacturerReference": {
    "reference": "Organization/Manufacturer35b3de1add41b53c8e37ce338f2ba545"
  },
  "responsibleNRAReference": {
    "reference": "Organization/Holderf79f23b4c5122fd96b2c87cc385157fc"
  },
  "productReference": {
    "reference": "http://smart.who.int/pcmt/StructureDefinition/Product/MenigococcalACYWXPolysacProduct62f4ead3da74f2f31a51006339af12fe"
  }
}